{"atomic_data":[{"type":"Name","label":"osqn","index":92,"is_public":false},{"type":"Symbol","label":"Sqn","arity":0,"category":"Constructor","is_public":true},{"type":"Symbol","label":"tuple2","arity":2,"category":"Tuple","is_public":true},{"type":"Name","label":"r","index":97,"is_public":false},{"type":"Name","label":"rand","index":96,"is_public":false},{"type":"Name","label":"k","index":91,"is_public":false},{"type":"Symbol","label":"f0","arity":2,"category":"Constructor","is_public":true},{"type":"Symbol","label":"senc","arity":3,"category":"Constructor","is_public":true},{"type":"Symbol","label":"imsi_wtn","arity":0,"category":"Constructor","is_public":true},{"type":"Symbol","label":"Fail","arity":0,"category":"Constructor","is_public":true},{"type":"Symbol","label":"tuple4","arity":4,"category":"Tuple","is_public":true},{"type":"Name","label":"r_ms","index":93,"is_public":false},{"type":"Variable","label":"pbN","index":216},{"type":"Symbol","label":"aenc","arity":3,"category":"Constructor","is_public":true},{"type":"Symbol","label":"chMS1","arity":0,"category":"Constructor","is_public":true},{"type":"Name","label":"r","index":95,"is_public":false},{"type":"Name","label":"rand","index":94,"is_public":false},{"type":"Variable","label":"xmsg","index":228},{"type":"Variable","label":"res","index":225},{"type":"Variable","label":"xrand","index":218},{"type":"Symbol","label":"f4","arity":2,"category":"Constructor","is_public":true},{"type":"Variable","label":"ik","index":227},{"type":"Symbol","label":"f3","arity":2,"category":"Constructor","is_public":true},{"type":"Variable","label":"ck","index":226},{"type":"Symbol","label":"f2","arity":2,"category":"Constructor","is_public":true},{"type":"Variable","label":"mac","index":224},{"type":"Variable","label":"xsqn","index":223},{"type":"Variable","label":"xmac","index":221},{"type":"Symbol","label":"f1","arity":2,"category":"Constructor","is_public":true},{"type":"Variable","label":"msg","index":220},{"type":"Variable","label":"ak","index":222},{"type":"Symbol","label":"sdec","arity":2,"category":"Destructor","is_public":true},{"type":"Symbol","label":"f5","arity":2,"category":"Constructor","is_public":true},{"type":"Variable","label":"xautn","index":219},{"type":"Variable","label":"x","index":217},{"type":"Symbol","label":"reject","arity":0,"category":"Constructor","is_public":true},{"type":"Symbol","label":"chSN1","arity":0,"category":"Constructor","is_public":true},{"type":"Name","label":"s","index":100,"is_public":false},{"type":"Name","label":"r","index":101,"is_public":false},{"type":"Variable","label":"ck","index":231},{"type":"Variable","label":"res","index":230},{"type":"Variable","label":"xres","index":236},{"type":"Variable","label":"autn","index":234},{"type":"Name","label":"rand","index":98,"is_public":false},{"type":"Variable","label":"ak","index":233},{"type":"Variable","label":"ik","index":232},{"type":"Symbol","label":"tuple5","arity":5,"category":"Tuple","is_public":true},{"type":"Variable","label":"av","index":235},{"type":"Variable","label":"mac","index":229},{"type":"Name","label":"r_sn","index":99,"is_public":false},{"type":"Name","label":"osqn","index":104,"is_public":false},{"type":"Name","label":"r","index":109,"is_public":false},{"type":"Name","label":"rand","index":108,"is_public":false},{"type":"Name","label":"k","index":102,"is_public":false},{"type":"Name","label":"imsi","index":103,"is_public":false},{"type":"Name","label":"r_ms","index":105,"is_public":false},{"type":"Symbol","label":"chMS2","arity":0,"category":"Constructor","is_public":true},{"type":"Name","label":"r","index":107,"is_public":false},{"type":"Name","label":"rand","index":106,"is_public":false},{"type":"Variable","label":"xmsg","index":248},{"type":"Variable","label":"res","index":245},{"type":"Variable","label":"xrand","index":238},{"type":"Variable","label":"ik","index":247},{"type":"Variable","label":"ck","index":246},{"type":"Variable","label":"mac","index":244},{"type":"Variable","label":"xsqn","index":243},{"type":"Variable","label":"xmac","index":241},{"type":"Variable","label":"msg","index":240},{"type":"Variable","label":"ak","index":242},{"type":"Variable","label":"xautn","index":239},{"type":"Variable","label":"x","index":237},{"type":"Symbol","label":"chSN2","arity":0,"category":"Constructor","is_public":true},{"type":"Name","label":"s","index":112,"is_public":false},{"type":"Name","label":"r","index":113,"is_public":false},{"type":"Variable","label":"ck","index":251},{"type":"Variable","label":"res","index":250},{"type":"Variable","label":"xres","index":256},{"type":"Variable","label":"autn","index":254},{"type":"Name","label":"rand","index":110,"is_public":false},{"type":"Variable","label":"ak","index":253},{"type":"Variable","label":"ik","index":252},{"type":"Variable","label":"av","index":255},{"type":"Variable","label":"mac","index":249},{"type":"Name","label":"r_sn","index":111,"is_public":false},{"type":"Symbol","label":"c","arity":0,"category":"Constructor","is_public":true},{"type":"Name","label":"pvN","index":90,"is_public":false},{"type":"Symbol","label":"pub","arity":1,"category":"Constructor","is_public":true},{"type":"Name","label":"osqn","index":70,"is_public":false},{"type":"Name","label":"r","index":75,"is_public":false},{"type":"Name","label":"rand","index":74,"is_public":false},{"type":"Name","label":"k","index":68,"is_public":false},{"type":"Name","label":"imsi","index":69,"is_public":false},{"type":"Name","label":"r_ms","index":71,"is_public":false},{"type":"Variable","label":"pbN","index":175},{"type":"Name","label":"r","index":73,"is_public":false},{"type":"Name","label":"rand","index":72,"is_public":false},{"type":"Variable","label":"xmsg","index":187},{"type":"Variable","label":"res","index":184},{"type":"Variable","label":"xrand","index":177},{"type":"Variable","label":"ik","index":186},{"type":"Variable","label":"ck","index":185},{"type":"Variable","label":"mac","index":183},{"type":"Variable","label":"xsqn","index":182},{"type":"Variable","label":"xmac","index":180},{"type":"Variable","label":"msg","index":179},{"type":"Variable","label":"ak","index":181},{"type":"Variable","label":"xautn","index":178},{"type":"Variable","label":"x","index":176},{"type":"Name","label":"s","index":78,"is_public":false},{"type":"Name","label":"r","index":79,"is_public":false},{"type":"Variable","label":"ck","index":190},{"type":"Variable","label":"res","index":189},{"type":"Variable","label":"xres","index":195},{"type":"Variable","label":"autn","index":193},{"type":"Name","label":"rand","index":76,"is_public":false},{"type":"Variable","label":"ak","index":192},{"type":"Variable","label":"ik","index":191},{"type":"Variable","label":"av","index":194},{"type":"Variable","label":"mac","index":188},{"type":"Name","label":"r_sn","index":77,"is_public":false},{"type":"Name","label":"osqn","index":80,"is_public":false},{"type":"Name","label":"r","index":85,"is_public":false},{"type":"Name","label":"rand","index":84,"is_public":false},{"type":"Name","label":"r_ms","index":81,"is_public":false},{"type":"Name","label":"r","index":83,"is_public":false},{"type":"Name","label":"rand","index":82,"is_public":false},{"type":"Variable","label":"xmsg","index":207},{"type":"Variable","label":"res","index":204},{"type":"Variable","label":"xrand","index":197},{"type":"Variable","label":"ik","index":206},{"type":"Variable","label":"ck","index":205},{"type":"Variable","label":"mac","index":203},{"type":"Variable","label":"xsqn","index":202},{"type":"Variable","label":"xmac","index":200},{"type":"Variable","label":"msg","index":199},{"type":"Variable","label":"ak","index":201},{"type":"Variable","label":"xautn","index":198},{"type":"Variable","label":"x","index":196},{"type":"Name","label":"s","index":88,"is_public":false},{"type":"Name","label":"r","index":89,"is_public":false},{"type":"Variable","label":"ck","index":210},{"type":"Variable","label":"res","index":209},{"type":"Variable","label":"xres","index":215},{"type":"Variable","label":"autn","index":213},{"type":"Name","label":"rand","index":86,"is_public":false},{"type":"Variable","label":"ak","index":212},{"type":"Variable","label":"ik","index":211},{"type":"Variable","label":"av","index":214},{"type":"Variable","label":"mac","index":208},{"type":"Name","label":"r_sn","index":87,"is_public":false},{"type":"Name","label":"pvN","index":67,"is_public":false}],"process1":{"type":"New","name":85,"position":{"index":77,"args":[]},"process":{"type":"LetInElse","pattern":{"type":"Atomic","id":12},"term":{"type":"Function","symbol":86,"args":[{"type":"Atomic","id":85}]},"position":{"index":76,"args":[]},"process_then":{"type":"Output","channel":{"type":"Function","symbol":84,"args":[]},"term":{"type":"Atomic","id":12},"position":{"index":75,"args":[]},"process":{"type":"Par","process_list":[{"type":"New","name":53,"position":{"index":74,"args":[]},"process":{"type":"New","name":54,"position":{"index":73,"args":[]},"process":{"type":"New","name":50,"position":{"index":72,"args":[]},"process":{"type":"Par","process_list":[{"type":"New","name":78,"position":{"index":71,"args":[]},"process":{"type":"New","name":83,"position":{"index":70,"args":[]},"process":{"type":"New","name":72,"position":{"index":69,"args":[]},"process":{"type":"New","name":73,"position":{"index":68,"args":[]},"process":{"type":"LetInElse","pattern":{"type":"Atomic","id":82},"term":{"type":"Function","symbol":28,"args":[{"type":"Atomic","id":53},{"type":"Function","symbol":2,"args":[{"type":"Atomic","id":78},{"type":"Atomic","id":50}]}]},"position":{"index":67,"args":[]},"process_then":{"type":"LetInElse","pattern":{"type":"Atomic","id":75},"term":{"type":"Function","symbol":24,"args":[{"type":"Atomic","id":53},{"type":"Atomic","id":78}]},"position":{"index":66,"args":[]},"process_then":{"type":"LetInElse","pattern":{"type":"Atomic","id":74},"term":{"type":"Function","symbol":22,"args":[{"type":"Atomic","id":53},{"type":"Atomic","id":78}]},"position":{"index":65,"args":[]},"process_then":{"type":"LetInElse","pattern":{"type":"Atomic","id":80},"term":{"type":"Function","symbol":20,"args":[{"type":"Atomic","id":53},{"type":"Atomic","id":78}]},"position":{"index":64,"args":[]},"process_then":{"type":"LetInElse","pattern":{"type":"Atomic","id":79},"term":{"type":"Function","symbol":32,"args":[{"type":"Atomic","id":53},{"type":"Atomic","id":78}]},"position":{"index":63,"args":[]},"process_then":{"type":"LetInElse","pattern":{"type":"Atomic","id":77},"term":{"type":"Function","symbol":2,"args":[{"type":"Function","symbol":7,"args":[{"type":"Atomic","id":79},{"type":"Atomic","id":83},{"type":"Atomic","id":50}]},{"type":"Atomic","id":82}]},"position":{"index":62,"args":[]},"process_then":{"type":"LetInElse","pattern":{"type":"Atomic","id":81},"term":{"type":"Function","symbol":46,"args":[{"type":"Atomic","id":78},{"type":"Atomic","id":75},{"type":"Atomic","id":74},{"type":"Atomic","id":80},{"type":"Atomic","id":79}]},"position":{"index":61,"args":[]},"process_then":{"type":"Output","channel":{"type":"Function","symbol":71,"args":[]},"term":{"type":"Function","symbol":2,"args":[{"type":"Atomic","id":78},{"type":"Atomic","id":77}]},"position":{"index":60,"args":[]},"process":{"type":"Input","channel":{"type":"Function","symbol":71,"args":[]},"pattern":{"type":"Atomic","id":76},"position":{"index":59,"args":[]},"process":{"type":"IfThenElse","term1":{"type":"Atomic","id":76},"term2":{"type":"Atomic","id":75},"position":{"index":58,"args":[]},"process_then":{"type":"Output","channel":{"type":"Function","symbol":71,"args":[]},"term":{"type":"Function","symbol":7,"args":[{"type":"Atomic","id":74},{"type":"Atomic","id":73},{"type":"Atomic","id":72}]},"position":{"index":56,"args":[]},"process":{"type":null}},"process_else":{"type":"Output","channel":{"type":"Function","symbol":71,"args":[]},"term":{"type":"Function","symbol":35,"args":[]},"position":{"index":57,"args":[]},"process":{"type":null}}}}},"process_else":{"type":null}},"process_else":{"type":null}},"process_else":{"type":null}},"process_else":{"type":null}},"process_else":{"type":null}},"process_else":{"type":null}},"process_else":{"type":null}}}}}},{"type":"New","name":55,"position":{"index":55,"args":[]},"process":{"type":"Input","channel":{"type":"Function","symbol":56,"args":[]},"pattern":{"type":"Atomic","id":70},"position":{"index":54,"args":[]},"process":{"type":"LetInElse","pattern":{"type":"Function","symbol":2,"args":[{"type":"Atomic","id":61},{"type":"Atomic","id":69}]},"term":{"type":"Atomic","id":70},"position":{"index":53,"args":[]},"process_then":{"type":"LetInElse","pattern":{"type":"Function","symbol":2,"args":[{"type":"Atomic","id":67},{"type":"Atomic","id":66}]},"term":{"type":"Atomic","id":69},"position":{"index":52,"args":[]},"process_then":{"type":"LetInElse","pattern":{"type":"Atomic","id":68},"term":{"type":"Function","symbol":32,"args":[{"type":"Atomic","id":53},{"type":"Atomic","id":61}]},"position":{"index":51,"args":[]},"process_then":{"type":"LetInElse","pattern":{"type":"Atomic","id":65},"term":{"type":"Function","symbol":31,"args":[{"type":"Atomic","id":68},{"type":"Atomic","id":67}]},"position":{"index":50,"args":[]},"process_then":{"type":"LetInElse","pattern":{"type":"Atomic","id":64},"term":{"type":"Function","symbol":28,"args":[{"type":"Atomic","id":53},{"type":"Function","symbol":2,"args":[{"type":"Atomic","id":61},{"type":"Atomic","id":65}]}]},"position":{"index":46,"args":[]},"process_then":{"type":"IfThenElse","term1":{"type":"Function","symbol":2,"args":[{"type":"Atomic","id":66},{"type":"Atomic","id":65}]},"term2":{"type":"Function","symbol":2,"args":[{"type":"Atomic","id":64},{"type":"Atomic","id":50}]},"position":{"index":45,"args":[]},"process_then":{"type":"LetInElse","pattern":{"type":"Atomic","id":60},"term":{"type":"Function","symbol":24,"args":[{"type":"Atomic","id":53},{"type":"Atomic","id":61}]},"position":{"index":41,"args":[]},"process_then":{"type":"LetInElse","pattern":{"type":"Atomic","id":63},"term":{"type":"Function","symbol":22,"args":[{"type":"Atomic","id":53},{"type":"Atomic","id":61}]},"position":{"index":40,"args":[]},"process_then":{"type":"LetInElse","pattern":{"type":"Atomic","id":62},"term":{"type":"Function","symbol":20,"args":[{"type":"Atomic","id":53},{"type":"Atomic","id":61}]},"position":{"index":39,"args":[]},"process_then":{"type":"Output","channel":{"type":"Function","symbol":56,"args":[]},"term":{"type":"Atomic","id":60},"position":{"index":38,"args":[]},"process":{"type":"Input","channel":{"type":"Function","symbol":56,"args":[]},"pattern":{"type":"Atomic","id":59},"position":{"index":37,"args":[]},"process":{"type":null}}},"process_else":{"type":null}},"process_else":{"type":null}},"process_else":{"type":null}},"process_else":{"type":"New","name":58,"position":{"index":44,"args":[]},"process":{"type":"New","name":57,"position":{"index":43,"args":[]},"process":{"type":"Output","channel":{"type":"Function","symbol":56,"args":[]},"term":{"type":"Function","symbol":13,"args":[{"type":"Atomic","id":12},{"type":"Atomic","id":55},{"type":"Function","symbol":10,"args":[{"type":"Function","symbol":9,"args":[]},{"type":"Atomic","id":54},{"type":"Atomic","id":58},{"type":"Function","symbol":7,"args":[{"type":"Function","symbol":6,"args":[{"type":"Atomic","id":53},{"type":"Atomic","id":58}]},{"type":"Atomic","id":57},{"type":"Function","symbol":2,"args":[{"type":"Function","symbol":1,"args":[]},{"type":"Atomic","id":50}]}]}]}]},"position":{"index":42,"args":[]},"process":{"type":null}}}}},"process_else":{"type":null}},"process_else":{"type":"New","name":52,"position":{"index":49,"args":[]},"process":{"type":"New","name":51,"position":{"index":48,"args":[]},"process":{"type":"Output","channel":{"type":"Function","symbol":56,"args":[]},"term":{"type":"Function","symbol":13,"args":[{"type":"Atomic","id":12},{"type":"Atomic","id":55},{"type":"Function","symbol":10,"args":[{"type":"Function","symbol":9,"args":[]},{"type":"Atomic","id":54},{"type":"Atomic","id":52},{"type":"Function","symbol":7,"args":[{"type":"Function","symbol":6,"args":[{"type":"Atomic","id":53},{"type":"Atomic","id":52}]},{"type":"Atomic","id":51},{"type":"Function","symbol":2,"args":[{"type":"Function","symbol":1,"args":[]},{"type":"Atomic","id":50}]}]}]}]},"position":{"index":47,"args":[]},"process":{"type":null}}}}},"process_else":{"type":null}},"process_else":{"type":null}},"process_else":{"type":null}}}}]}}}},{"type":"New","name":5,"position":{"index":36,"args":[]},"process":{"type":"New","name":0,"position":{"index":35,"args":[]},"process":{"type":"Par","process_list":[{"type":"New","name":43,"position":{"index":34,"args":[]},"process":{"type":"New","name":49,"position":{"index":33,"args":[]},"process":{"type":"New","name":37,"position":{"index":32,"args":[]},"process":{"type":"New","name":38,"position":{"index":31,"args":[]},"process":{"type":"LetInElse","pattern":{"type":"Atomic","id":48},"term":{"type":"Function","symbol":28,"args":[{"type":"Atomic","id":5},{"type":"Function","symbol":2,"args":[{"type":"Atomic","id":43},{"type":"Atomic","id":0}]}]},"position":{"index":30,"args":[]},"process_then":{"type":"LetInElse","pattern":{"type":"Atomic","id":40},"term":{"type":"Function","symbol":24,"args":[{"type":"Atomic","id":5},{"type":"Atomic","id":43}]},"position":{"index":29,"args":[]},"process_then":{"type":"LetInElse","pattern":{"type":"Atomic","id":39},"term":{"type":"Function","symbol":22,"args":[{"type":"Atomic","id":5},{"type":"Atomic","id":43}]},"position":{"index":28,"args":[]},"process_then":{"type":"LetInElse","pattern":{"type":"Atomic","id":45},"term":{"type":"Function","symbol":20,"args":[{"type":"Atomic","id":5},{"type":"Atomic","id":43}]},"position":{"index":27,"args":[]},"process_then":{"type":"LetInElse","pattern":{"type":"Atomic","id":44},"term":{"type":"Function","symbol":32,"args":[{"type":"Atomic","id":5},{"type":"Atomic","id":43}]},"position":{"index":26,"args":[]},"process_then":{"type":"LetInElse","pattern":{"type":"Atomic","id":42},"term":{"type":"Function","symbol":2,"args":[{"type":"Function","symbol":7,"args":[{"type":"Atomic","id":44},{"type":"Atomic","id":49},{"type":"Atomic","id":0}]},{"type":"Atomic","id":48}]},"position":{"index":25,"args":[]},"process_then":{"type":"LetInElse","pattern":{"type":"Atomic","id":47},"term":{"type":"Function","symbol":46,"args":[{"type":"Atomic","id":43},{"type":"Atomic","id":40},{"type":"Atomic","id":39},{"type":"Atomic","id":45},{"type":"Atomic","id":44}]},"position":{"index":24,"args":[]},"process_then":{"type":"Output","channel":{"type":"Function","symbol":36,"args":[]},"term":{"type":"Function","symbol":2,"args":[{"type":"Atomic","id":43},{"type":"Atomic","id":42}]},"position":{"index":23,"args":[]},"process":{"type":"Input","channel":{"type":"Function","symbol":36,"args":[]},"pattern":{"type":"Atomic","id":41},"position":{"index":22,"args":[]},"process":{"type":"IfThenElse","term1":{"type":"Atomic","id":41},"term2":{"type":"Atomic","id":40},"position":{"index":21,"args":[]},"process_then":{"type":"Output","channel":{"type":"Function","symbol":36,"args":[]},"term":{"type":"Function","symbol":7,"args":[{"type":"Atomic","id":39},{"type":"Atomic","id":38},{"type":"Atomic","id":37}]},"position":{"index":19,"args":[]},"process":{"type":null}},"process_else":{"type":"Output","channel":{"type":"Function","symbol":36,"args":[]},"term":{"type":"Function","symbol":35,"args":[]},"position":{"index":20,"args":[]},"process":{"type":null}}}}},"process_else":{"type":null}},"process_else":{"type":null}},"process_else":{"type":null}},"process_else":{"type":null}},"process_else":{"type":null}},"process_else":{"type":null}},"process_else":{"type":null}}}}}},{"type":"New","name":11,"position":{"index":18,"args":[]},"process":{"type":"Input","channel":{"type":"Function","symbol":14,"args":[]},"pattern":{"type":"Atomic","id":34},"position":{"index":17,"args":[]},"process":{"type":"LetInElse","pattern":{"type":"Function","symbol":2,"args":[{"type":"Atomic","id":19},{"type":"Atomic","id":33}]},"term":{"type":"Atomic","id":34},"position":{"index":16,"args":[]},"process_then":{"type":"LetInElse","pattern":{"type":"Function","symbol":2,"args":[{"type":"Atomic","id":29},{"type":"Atomic","id":27}]},"term":{"type":"Atomic","id":33},"position":{"index":15,"args":[]},"process_then":{"type":"LetInElse","pattern":{"type":"Atomic","id":30},"term":{"type":"Function","symbol":32,"args":[{"type":"Atomic","id":5},{"type":"Atomic","id":19}]},"position":{"index":14,"args":[]},"process_then":{"type":"LetInElse","pattern":{"type":"Atomic","id":26},"term":{"type":"Function","symbol":31,"args":[{"type":"Atomic","id":30},{"type":"Atomic","id":29}]},"position":{"index":13,"args":[]},"process_then":{"type":"LetInElse","pattern":{"type":"Atomic","id":25},"term":{"type":"Function","symbol":28,"args":[{"type":"Atomic","id":5},{"type":"Function","symbol":2,"args":[{"type":"Atomic","id":19},{"type":"Atomic","id":26}]}]},"position":{"index":9,"args":[]},"process_then":{"type":"IfThenElse","term1":{"type":"Function","symbol":2,"args":[{"type":"Atomic","id":27},{"type":"Atomic","id":26}]},"term2":{"type":"Function","symbol":2,"args":[{"type":"Atomic","id":25},{"type":"Atomic","id":0}]},"position":{"index":8,"args":[]},"process_then":{"type":"LetInElse","pattern":{"type":"Atomic","id":18},"term":{"type":"Function","symbol":24,"args":[{"type":"Atomic","id":5},{"type":"Atomic","id":19}]},"position":{"index":4,"args":[]},"process_then":{"type":"LetInElse","pattern":{"type":"Atomic","id":23},"term":{"type":"Function","symbol":22,"args":[{"type":"Atomic","id":5},{"type":"Atomic","id":19}]},"position":{"index":3,"args":[]},"process_then":{"type":"LetInElse","pattern":{"type":"Atomic","id":21},"term":{"type":"Function","symbol":20,"args":[{"type":"Atomic","id":5},{"type":"Atomic","id":19}]},"position":{"index":2,"args":[]},"process_then":{"type":"Output","channel":{"type":"Function","symbol":14,"args":[]},"term":{"type":"Atomic","id":18},"position":{"index":1,"args":[]},"process":{"type":"Input","channel":{"type":"Function","symbol":14,"args":[]},"pattern":{"type":"Atomic","id":17},"position":{"index":0,"args":[]},"process":{"type":null}}},"process_else":{"type":null}},"process_else":{"type":null}},"process_else":{"type":null}},"process_else":{"type":"New","name":16,"position":{"index":7,"args":[]},"process":{"type":"New","name":15,"position":{"index":6,"args":[]},"process":{"type":"Output","channel":{"type":"Function","symbol":14,"args":[]},"term":{"type":"Function","symbol":13,"args":[{"type":"Atomic","id":12},{"type":"Atomic","id":11},{"type":"Function","symbol":10,"args":[{"type":"Function","symbol":9,"args":[]},{"type":"Function","symbol":8,"args":[]},{"type":"Atomic","id":16},{"type":"Function","symbol":7,"args":[{"type":"Function","symbol":6,"args":[{"type":"Atomic","id":5},{"type":"Atomic","id":16}]},{"type":"Atomic","id":15},{"type":"Function","symbol":2,"args":[{"type":"Function","symbol":1,"args":[]},{"type":"Atomic","id":0}]}]}]}]},"position":{"index":5,"args":[]},"process":{"type":null}}}}},"process_else":{"type":null}},"process_else":{"type":"New","name":4,"position":{"index":12,"args":[]},"process":{"type":"New","name":3,"position":{"index":11,"args":[]},"process":{"type":"Output","channel":{"type":"Function","symbol":14,"args":[]},"term":{"type":"Function","symbol":13,"args":[{"type":"Atomic","id":12},{"type":"Atomic","id":11},{"type":"Function","symbol":10,"args":[{"type":"Function","symbol":9,"args":[]},{"type":"Function","symbol":8,"args":[]},{"type":"Atomic","id":4},{"type":"Function","symbol":7,"args":[{"type":"Function","symbol":6,"args":[{"type":"Atomic","id":5},{"type":"Atomic","id":4}]},{"type":"Atomic","id":3},{"type":"Function","symbol":2,"args":[{"type":"Function","symbol":1,"args":[]},{"type":"Atomic","id":0}]}]}]}]},"position":{"index":10,"args":[]},"process":{"type":null}}}}},"process_else":{"type":null}},"process_else":{"type":null}},"process_else":{"type":null}}}}]}}}]}},"process_else":{"type":null}}},"process2":{"type":"New","name":150,"position":{"index":154,"args":[]},"process":{"type":"LetInElse","pattern":{"type":"Atomic","id":93},"term":{"type":"Function","symbol":86,"args":[{"type":"Atomic","id":150}]},"position":{"index":153,"args":[]},"process_then":{"type":"Output","channel":{"type":"Function","symbol":84,"args":[]},"term":{"type":"Atomic","id":93},"position":{"index":152,"args":[]},"process":{"type":"New","name":90,"position":{"index":151,"args":[]},"process":{"type":"New","name":91,"position":{"index":150,"args":[]},"process":{"type":"Par","process_list":[{"type":"New","name":120,"position":{"index":149,"args":[]},"process":{"type":"Par","process_list":[{"type":"New","name":144,"position":{"index":148,"args":[]},"process":{"type":"New","name":149,"position":{"index":147,"args":[]},"process":{"type":"New","name":138,"position":{"index":146,"args":[]},"process":{"type":"New","name":139,"position":{"index":145,"args":[]},"process":{"type":"LetInElse","pattern":{"type":"Atomic","id":148},"term":{"type":"Function","symbol":28,"args":[{"type":"Atomic","id":90},{"type":"Function","symbol":2,"args":[{"type":"Atomic","id":144},{"type":"Atomic","id":120}]}]},"position":{"index":144,"args":[]},"process_then":{"type":"LetInElse","pattern":{"type":"Atomic","id":141},"term":{"type":"Function","symbol":24,"args":[{"type":"Atomic","id":90},{"type":"Atomic","id":144}]},"position":{"index":143,"args":[]},"process_then":{"type":"LetInElse","pattern":{"type":"Atomic","id":140},"term":{"type":"Function","symbol":22,"args":[{"type":"Atomic","id":90},{"type":"Atomic","id":144}]},"position":{"index":142,"args":[]},"process_then":{"type":"LetInElse","pattern":{"type":"Atomic","id":146},"term":{"type":"Function","symbol":20,"args":[{"type":"Atomic","id":90},{"type":"Atomic","id":144}]},"position":{"index":141,"args":[]},"process_then":{"type":"LetInElse","pattern":{"type":"Atomic","id":145},"term":{"type":"Function","symbol":32,"args":[{"type":"Atomic","id":90},{"type":"Atomic","id":144}]},"position":{"index":140,"args":[]},"process_then":{"type":"LetInElse","pattern":{"type":"Atomic","id":143},"term":{"type":"Function","symbol":2,"args":[{"type":"Function","symbol":7,"args":[{"type":"Atomic","id":145},{"type":"Atomic","id":149},{"type":"Atomic","id":120}]},{"type":"Atomic","id":148}]},"position":{"index":139,"args":[]},"process_then":{"type":"LetInElse","pattern":{"type":"Atomic","id":147},"term":{"type":"Function","symbol":46,"args":[{"type":"Atomic","id":144},{"type":"Atomic","id":141},{"type":"Atomic","id":140},{"type":"Atomic","id":146},{"type":"Atomic","id":145}]},"position":{"index":138,"args":[]},"process_then":{"type":"Output","channel":{"type":"Function","symbol":71,"args":[]},"term":{"type":"Function","symbol":2,"args":[{"type":"Atomic","id":144},{"type":"Atomic","id":143}]},"position":{"index":137,"args":[]},"process":{"type":"Input","channel":{"type":"Function","symbol":71,"args":[]},"pattern":{"type":"Atomic","id":142},"position":{"index":136,"args":[]},"process":{"type":"IfThenElse","term1":{"type":"Atomic","id":142},"term2":{"type":"Atomic","id":141},"position":{"index":135,"args":[]},"process_then":{"type":"Output","channel":{"type":"Function","symbol":71,"args":[]},"term":{"type":"Function","symbol":7,"args":[{"type":"Atomic","id":140},{"type":"Atomic","id":139},{"type":"Atomic","id":138}]},"position":{"index":133,"args":[]},"process":{"type":null}},"process_else":{"type":"Output","channel":{"type":"Function","symbol":71,"args":[]},"term":{"type":"Function","symbol":35,"args":[]},"position":{"index":134,"args":[]},"process":{"type":null}}}}},"process_else":{"type":null}},"process_else":{"type":null}},"process_else":{"type":null}},"process_else":{"type":null}},"process_else":{"type":null}},"process_else":{"type":null}},"process_else":{"type":null}}}}}},{"type":"New","name":123,"position":{"index":132,"args":[]},"process":{"type":"Input","channel":{"type":"Function","symbol":56,"args":[]},"pattern":{"type":"Atomic","id":137},"position":{"index":131,"args":[]},"process":{"type":"LetInElse","pattern":{"type":"Function","symbol":2,"args":[{"type":"Atomic","id":128},{"type":"Atomic","id":136}]},"term":{"type":"Atomic","id":137},"position":{"index":130,"args":[]},"process_then":{"type":"LetInElse","pattern":{"type":"Function","symbol":2,"args":[{"type":"Atomic","id":134},{"type":"Atomic","id":133}]},"term":{"type":"Atomic","id":136},"position":{"index":129,"args":[]},"process_then":{"type":"LetInElse","pattern":{"type":"Atomic","id":135},"term":{"type":"Function","symbol":32,"args":[{"type":"Atomic","id":90},{"type":"Atomic","id":128}]},"position":{"index":128,"args":[]},"process_then":{"type":"LetInElse","pattern":{"type":"Atomic","id":132},"term":{"type":"Function","symbol":31,"args":[{"type":"Atomic","id":135},{"type":"Atomic","id":134}]},"position":{"index":127,"args":[]},"process_then":{"type":"LetInElse","pattern":{"type":"Atomic","id":131},"term":{"type":"Function","symbol":28,"args":[{"type":"Atomic","id":90},{"type":"Function","symbol":2,"args":[{"type":"Atomic","id":128},{"type":"Atomic","id":132}]}]},"position":{"index":123,"args":[]},"process_then":{"type":"IfThenElse","term1":{"type":"Function","symbol":2,"args":[{"type":"Atomic","id":133},{"type":"Atomic","id":132}]},"term2":{"type":"Function","symbol":2,"args":[{"type":"Atomic","id":131},{"type":"Atomic","id":120}]},"position":{"index":122,"args":[]},"process_then":{"type":"LetInElse","pattern":{"type":"Atomic","id":127},"term":{"type":"Function","symbol":24,"args":[{"type":"Atomic","id":90},{"type":"Atomic","id":128}]},"position":{"index":118,"args":[]},"process_then":{"type":"LetInElse","pattern":{"type":"Atomic","id":130},"term":{"type":"Function","symbol":22,"args":[{"type":"Atomic","id":90},{"type":"Atomic","id":128}]},"position":{"index":117,"args":[]},"process_then":{"type":"LetInElse","pattern":{"type":"Atomic","id":129},"term":{"type":"Function","symbol":20,"args":[{"type":"Atomic","id":90},{"type":"Atomic","id":128}]},"position":{"index":116,"args":[]},"process_then":{"type":"Output","channel":{"type":"Function","symbol":56,"args":[]},"term":{"type":"Atomic","id":127},"position":{"index":115,"args":[]},"process":{"type":"Input","channel":{"type":"Function","symbol":56,"args":[]},"pattern":{"type":"Atomic","id":126},"position":{"index":114,"args":[]},"process":{"type":null}}},"process_else":{"type":null}},"process_else":{"type":null}},"process_else":{"type":null}},"process_else":{"type":"New","name":125,"position":{"index":121,"args":[]},"process":{"type":"New","name":124,"position":{"index":120,"args":[]},"process":{"type":"Output","channel":{"type":"Function","symbol":56,"args":[]},"term":{"type":"Function","symbol":13,"args":[{"type":"Atomic","id":93},{"type":"Atomic","id":123},{"type":"Function","symbol":10,"args":[{"type":"Function","symbol":9,"args":[]},{"type":"Atomic","id":91},{"type":"Atomic","id":125},{"type":"Function","symbol":7,"args":[{"type":"Function","symbol":6,"args":[{"type":"Atomic","id":90},{"type":"Atomic","id":125}]},{"type":"Atomic","id":124},{"type":"Function","symbol":2,"args":[{"type":"Function","symbol":1,"args":[]},{"type":"Atomic","id":120}]}]}]}]},"position":{"index":119,"args":[]},"process":{"type":null}}}}},"process_else":{"type":null}},"process_else":{"type":"New","name":122,"position":{"index":126,"args":[]},"process":{"type":"New","name":121,"position":{"index":125,"args":[]},"process":{"type":"Output","channel":{"type":"Function","symbol":56,"args":[]},"term":{"type":"Function","symbol":13,"args":[{"type":"Atomic","id":93},{"type":"Atomic","id":123},{"type":"Function","symbol":10,"args":[{"type":"Function","symbol":9,"args":[]},{"type":"Atomic","id":91},{"type":"Atomic","id":122},{"type":"Function","symbol":7,"args":[{"type":"Function","symbol":6,"args":[{"type":"Atomic","id":90},{"type":"Atomic","id":122}]},{"type":"Atomic","id":121},{"type":"Function","symbol":2,"args":[{"type":"Function","symbol":1,"args":[]},{"type":"Atomic","id":120}]}]}]}]},"position":{"index":124,"args":[]},"process":{"type":null}}}}},"process_else":{"type":null}},"process_else":{"type":null}},"process_else":{"type":null}}}}]}},{"type":"New","name":87,"position":{"index":113,"args":[]},"process":{"type":"Par","process_list":[{"type":"New","name":114,"position":{"index":112,"args":[]},"process":{"type":"New","name":119,"position":{"index":111,"args":[]},"process":{"type":"New","name":108,"position":{"index":110,"args":[]},"process":{"type":"New","name":109,"position":{"index":109,"args":[]},"process":{"type":"LetInElse","pattern":{"type":"Atomic","id":118},"term":{"type":"Function","symbol":28,"args":[{"type":"Atomic","id":90},{"type":"Function","symbol":2,"args":[{"type":"Atomic","id":114},{"type":"Atomic","id":87}]}]},"position":{"index":108,"args":[]},"process_then":{"type":"LetInElse","pattern":{"type":"Atomic","id":111},"term":{"type":"Function","symbol":24,"args":[{"type":"Atomic","id":90},{"type":"Atomic","id":114}]},"position":{"index":107,"args":[]},"process_then":{"type":"LetInElse","pattern":{"type":"Atomic","id":110},"term":{"type":"Function","symbol":22,"args":[{"type":"Atomic","id":90},{"type":"Atomic","id":114}]},"position":{"index":106,"args":[]},"process_then":{"type":"LetInElse","pattern":{"type":"Atomic","id":116},"term":{"type":"Function","symbol":20,"args":[{"type":"Atomic","id":90},{"type":"Atomic","id":114}]},"position":{"index":105,"args":[]},"process_then":{"type":"LetInElse","pattern":{"type":"Atomic","id":115},"term":{"type":"Function","symbol":32,"args":[{"type":"Atomic","id":90},{"type":"Atomic","id":114}]},"position":{"index":104,"args":[]},"process_then":{"type":"LetInElse","pattern":{"type":"Atomic","id":113},"term":{"type":"Function","symbol":2,"args":[{"type":"Function","symbol":7,"args":[{"type":"Atomic","id":115},{"type":"Atomic","id":119},{"type":"Atomic","id":87}]},{"type":"Atomic","id":118}]},"position":{"index":103,"args":[]},"process_then":{"type":"LetInElse","pattern":{"type":"Atomic","id":117},"term":{"type":"Function","symbol":46,"args":[{"type":"Atomic","id":114},{"type":"Atomic","id":111},{"type":"Atomic","id":110},{"type":"Atomic","id":116},{"type":"Atomic","id":115}]},"position":{"index":102,"args":[]},"process_then":{"type":"Output","channel":{"type":"Function","symbol":36,"args":[]},"term":{"type":"Function","symbol":2,"args":[{"type":"Atomic","id":114},{"type":"Atomic","id":113}]},"position":{"index":101,"args":[]},"process":{"type":"Input","channel":{"type":"Function","symbol":36,"args":[]},"pattern":{"type":"Atomic","id":112},"position":{"index":100,"args":[]},"process":{"type":"IfThenElse","term1":{"type":"Atomic","id":112},"term2":{"type":"Atomic","id":111},"position":{"index":99,"args":[]},"process_then":{"type":"Output","channel":{"type":"Function","symbol":36,"args":[]},"term":{"type":"Function","symbol":7,"args":[{"type":"Atomic","id":110},{"type":"Atomic","id":109},{"type":"Atomic","id":108}]},"position":{"index":97,"args":[]},"process":{"type":null}},"process_else":{"type":"Output","channel":{"type":"Function","symbol":36,"args":[]},"term":{"type":"Function","symbol":35,"args":[]},"position":{"index":98,"args":[]},"process":{"type":null}}}}},"process_else":{"type":null}},"process_else":{"type":null}},"process_else":{"type":null}},"process_else":{"type":null}},"process_else":{"type":null}},"process_else":{"type":null}},"process_else":{"type":null}}}}}},{"type":"New","name":92,"position":{"index":96,"args":[]},"process":{"type":"Input","channel":{"type":"Function","symbol":14,"args":[]},"pattern":{"type":"Atomic","id":107},"position":{"index":95,"args":[]},"process":{"type":"LetInElse","pattern":{"type":"Function","symbol":2,"args":[{"type":"Atomic","id":98},{"type":"Atomic","id":106}]},"term":{"type":"Atomic","id":107},"position":{"index":94,"args":[]},"process_then":{"type":"LetInElse","pattern":{"type":"Function","symbol":2,"args":[{"type":"Atomic","id":104},{"type":"Atomic","id":103}]},"term":{"type":"Atomic","id":106},"position":{"index":93,"args":[]},"process_then":{"type":"LetInElse","pattern":{"type":"Atomic","id":105},"term":{"type":"Function","symbol":32,"args":[{"type":"Atomic","id":90},{"type":"Atomic","id":98}]},"position":{"index":92,"args":[]},"process_then":{"type":"LetInElse","pattern":{"type":"Atomic","id":102},"term":{"type":"Function","symbol":31,"args":[{"type":"Atomic","id":105},{"type":"Atomic","id":104}]},"position":{"index":91,"args":[]},"process_then":{"type":"LetInElse","pattern":{"type":"Atomic","id":101},"term":{"type":"Function","symbol":28,"args":[{"type":"Atomic","id":90},{"type":"Function","symbol":2,"args":[{"type":"Atomic","id":98},{"type":"Atomic","id":102}]}]},"position":{"index":87,"args":[]},"process_then":{"type":"IfThenElse","term1":{"type":"Function","symbol":2,"args":[{"type":"Atomic","id":103},{"type":"Atomic","id":102}]},"term2":{"type":"Function","symbol":2,"args":[{"type":"Atomic","id":101},{"type":"Atomic","id":87}]},"position":{"index":86,"args":[]},"process_then":{"type":"LetInElse","pattern":{"type":"Atomic","id":97},"term":{"type":"Function","symbol":24,"args":[{"type":"Atomic","id":90},{"type":"Atomic","id":98}]},"position":{"index":82,"args":[]},"process_then":{"type":"LetInElse","pattern":{"type":"Atomic","id":100},"term":{"type":"Function","symbol":22,"args":[{"type":"Atomic","id":90},{"type":"Atomic","id":98}]},"position":{"index":81,"args":[]},"process_then":{"type":"LetInElse","pattern":{"type":"Atomic","id":99},"term":{"type":"Function","symbol":20,"args":[{"type":"Atomic","id":90},{"type":"Atomic","id":98}]},"position":{"index":80,"args":[]},"process_then":{"type":"Output","channel":{"type":"Function","symbol":14,"args":[]},"term":{"type":"Atomic","id":97},"position":{"index":79,"args":[]},"process":{"type":"Input","channel":{"type":"Function","symbol":14,"args":[]},"pattern":{"type":"Atomic","id":96},"position":{"index":78,"args":[]},"process":{"type":null}}},"process_else":{"type":null}},"process_else":{"type":null}},"process_else":{"type":null}},"process_else":{"type":"New","name":95,"position":{"index":85,"args":[]},"process":{"type":"New","name":94,"position":{"index":84,"args":[]},"process":{"type":"Output","channel":{"type":"Function","symbol":14,"args":[]},"term":{"type":"Function","symbol":13,"args":[{"type":"Atomic","id":93},{"type":"Atomic","id":92},{"type":"Function","symbol":10,"args":[{"type":"Function","symbol":9,"args":[]},{"type":"Atomic","id":91},{"type":"Atomic","id":95},{"type":"Function","symbol":7,"args":[{"type":"Function","symbol":6,"args":[{"type":"Atomic","id":90},{"type":"Atomic","id":95}]},{"type":"Atomic","id":94},{"type":"Function","symbol":2,"args":[{"type":"Function","symbol":1,"args":[]},{"type":"Atomic","id":87}]}]}]}]},"position":{"index":83,"args":[]},"process":{"type":null}}}}},"process_else":{"type":null}},"process_else":{"type":"New","name":89,"position":{"index":90,"args":[]},"process":{"type":"New","name":88,"position":{"index":89,"args":[]},"process":{"type":"Output","channel":{"type":"Function","symbol":14,"args":[]},"term":{"type":"Function","symbol":13,"args":[{"type":"Atomic","id":93},{"type":"Atomic","id":92},{"type":"Function","symbol":10,"args":[{"type":"Function","symbol":9,"args":[]},{"type":"Atomic","id":91},{"type":"Atomic","id":89},{"type":"Function","symbol":7,"args":[{"type":"Function","symbol":6,"args":[{"type":"Atomic","id":90},{"type":"Atomic","id":89}]},{"type":"Atomic","id":88},{"type":"Function","symbol":2,"args":[{"type":"Function","symbol":1,"args":[]},{"type":"Atomic","id":87}]}]}]}]},"position":{"index":88,"args":[]},"process":{"type":null}}}}},"process_else":{"type":null}},"process_else":{"type":null}},"process_else":{"type":null}}}}]}}]}}}},"process_else":{"type":null}}}}
